freeipa/__init__.py
freeipa/admin.py
freeipa/apps.py
freeipa/freeipa.py
freeipa/models.py
freeipa/settings.py
freeipa/tests.py
freeipa/views.py
freeipa/auth/__init__.py
freeipa/auth/backends.py
freeipa/auth/utils.py
freeipa/management/__init__.py
freeipa/management/commands/__init__.py
freeipa/management/commands/syncipa.py
freeipa/migrations/__init__.py
django_freeipa_auth_json-0.1.2.dev1.dist-info/LICENSE
django_freeipa_auth_json-0.1.2.dev1.dist-info/METADATA
django_freeipa_auth_json-0.1.2.dev1.dist-info/WHEEL
django_freeipa_auth_json-0.1.2.dev1.dist-info/top_level.txt
django_freeipa_auth_json-0.1.2.dev1.dist-info/RECORD
