Metadata-Version: 2.1
Name: django-freeipa-auth-json
Version: 0.1.2.dev1
Summary: FreeIPA authentication for Django using FreeIPA JSON API
Home-page: https://github.com/puttsk/django-freeipa-auth
Author: Putt Sakdhnagool
Author-email: putt.sakdhnagool@nectec.or.th
License: UNKNOWN
Project-URL: Bug Reports, https://github.com/puttsk/slurm-sbalance/issues
Project-URL: Source, https://github.com/puttsk/slurm-sbalance/
Keywords: django freeipa authentication
Platform: UNKNOWN
Classifier: Development Status :: 3 - Alpha
Classifier: License :: OSI Approved :: MIT License
Classifier: Programming Language :: Python :: 3
Classifier: Programming Language :: Python :: 3.6
Classifier: Topic :: Software Development :: Libraries :: Python Modules
Requires-Python: >=2.7, !=3.0.*, !=3.1.*, !=3.2.*, !=3.3.*, !=3.4.*, !=3.5.*, <4
